powermap/__init__.py
powermap/client.py
powermap/exceptions.py
powermap-0.1.0.dist-info/licenses/LICENSE
powermap-0.1.0.dist-info/METADATA
powermap-0.1.0.dist-info/WHEEL
powermap-0.1.0.dist-info/top_level.txt
powermap-0.1.0.dist-info/RECORD
